{"stats":{"minecraft:used":{"minecraft:diamond_pickaxe":14,"minecraft:firework_rocket":5,"minecraft:gray_shulker_box":3,"minecraft:yellow_shulker_box":4,"minecraft:purple_shulker_box":1,"minecraft:white_shulker_box":3,"minecraft:cooked_chicken":1,"minecraft:diamond_block":3},"minecraft:dropped":{"minecraft:stone":56,"minecraft:iron_nugget":3,"minecraft:diamond_leggings":1,"minecraft:chest":2,"minecraft:diamond_helmet":1,"minecraft:book":6,"minecraft:diamond_boots":1,"minecraft:arrow":15,"minecraft:white_concrete_powder":292},"minecraft:picked_up":{"minecraft:yellow_shulker_box":4,"minecraft:purple_shulker_box":1,"minecraft:diamond_block":46,"minecraft:gray_shulker_box":3,"minecraft:arrow":15,"minecraft:diamond":22,"minecraft:diamond_leggings":1,"minecraft:diamond_boots":1,"minecraft:iron_nugget":3,"minecraft:diamond_helmet":1,"minecraft:white_shulker_box":3},"minecraft:mined":{"minecraft:gray_shulker_box":3,"minecraft:diamond_block":3,"minecraft:purple_shulker_box":1,"minecraft:white_shulker_box":3,"minecraft:yellow_shulker_box":4},"minecraft:crafted":{"minecraft:diamond":25493},"minecraft:custom":{"minecraft:time_since_rest":63638,"minecraft:interact_with_furnace":3,"minecraft:sprint_one_cm":111467,"minecraft:damage_taken":189,"minecraft:walk_one_cm":133115,"minecraft:interact_with_anvil":1,"minecraft:drop":13,"minecraft:swim_one_cm":5510,"minecraft:fly_one_cm":121248,"minecraft:open_barrel":31,"minecraft:open_chest":45,"minecraft:crouch_one_cm":459,"minecraft:open_shulker_box":32,"minecraft:play_time":74337,"minecraft:sneak_time":222,"minecraft:walk_under_water_one_cm":13297,"minecraft:aviate_one_cm":73246,"minecraft:jump":435,"minecraft:leave_game":3,"minecraft:walk_on_water_one_cm":7226,"minecraft:time_since_death":74337,"minecraft:sleep_in_bed":1,"minecraft:climb_one_cm":7760,"minecraft:total_world_time":75342,"minecraft:fall_one_cm":8282,"minecraft:inspect_dispenser":70}},"DataVersion":3465}